mimicry/__init__.py
mimicry/admin.py
mimicry/app_settings.py
mimicry/apps.py
mimicry/checks.py
mimicry/context_processors.py
mimicry/forms.py
mimicry/middleware.py
mimicry/models.py
mimicry/signals.py
mimicry/tests.py
mimicry/urls.py
mimicry/utils.py
mimicry/views.py
mimicry/migrations/0001_initial.py
mimicry/migrations/__init__.py
mimicry/static/mimicry/css/styles.css
mimicry/static/mimicry/js/main.js
mimicry/templates/mimicry/mimicry_base.html
mimicry/templates/mimicry/simulation_email.html
mimicry/templates/mimicry/simulation_email.txt
mimicry/templates/mimicry/simulation_email_subject.txt
mimicry/templatetags/__init__.py
mimicry/templatetags/private_tags.py
django_mimicry-1.8.dist-info/LICENSE
django_mimicry-1.8.dist-info/METADATA
django_mimicry-1.8.dist-info/WHEEL
django_mimicry-1.8.dist-info/top_level.txt
django_mimicry-1.8.dist-info/RECORD
